{
  "config_id": "SC-WEEKLY-ELIM-FIRST_MEAL_2HR_DAILY",
  "config_name": "Weekly Elimination - first meal within 2 hours daily",
  "scoring_method": "weekly_elimination",
  "configuration_json": {
    "method": "weekly_elimination",
    "formula": "100 if all_days_meet_elimination_criteria else 0",
    "evaluation_pattern": "weekly_elimination",
    "schema": {
      "measurement_type": "weekly_elimination_achievement",
      "evaluation_period": "weekly_elimination",
      "success_criteria": "weekly_elimination_target",
      "calculation_method": "weekly_zero_tolerance",
      "tracked_metrics": [],
      "calculated_metrics": ["first_meal_delay"],
      "elimination_threshold": 2,
      "elimination_comparison": "<=",
      "success_value": 100,
      "failure_value": 0,
      "unit": "hours_minutes",
      "progress_direction": "measurement",
      "total_days": 7,
      "tolerance_level": "zero",
      "frequency_requirement": "daily",
      "description": "SC-WEEKLY-ELIMINATION: Daily pass/fail based on eating first meal within 2 hours of waking every day"
    }
  },
  "metadata": {
    "recommendation_text": "Eat your first meal of the day within 2 hours after waking every day of the week",
    "recommendation_id": "REC0018.3",
    "analysis": {
      "algorithm_type": "binary_threshold",
      "confidence": 0.9,
      "reasoning": "SC-WEEKLY-ELIMINATION: Daily evaluation pattern since requirement is every single day"
    },
    "metric_id": "first_meal_delay",
    "generated_at": "2024-01-15T10:30:00Z"
  }
}